MANIFEST.in
README.rst
setup.py
pyheaderfile/__init__.py
pyheaderfile/basefile.py
pyheaderfile/drive.py
pyheaderfile/excel.py
pyheaderfile/headercsv.py
pyheaderfile/helpers.py
pyheaderfile/libreoffice.py
pyheaderfile/utils.py
pyheaderfile.egg-info/PKG-INFO
pyheaderfile.egg-info/SOURCES.txt
pyheaderfile.egg-info/dependency_links.txt
pyheaderfile.egg-info/requires.txt
pyheaderfile.egg-info/top_level.txt