Metadata-Version: 1.1
Name: pyheaderfile
Version: 0.4.0
Summary: Enable handle of csv, xls and xlsx files getting column header
Home-page: https://github.com/kappius/pyheaderfile
Author: Diogo Munaro Vieira, Isvaldo Fernandes de Souza, Thiago Pereira Fernandes
Author-email: diogo.mvieira@gmail.com, isvaldo.fernandes@gmail.com, thiago.fernandes210@gmail.com
License: Apache
Download-URL: https://github.com/kappius/pyheaderfile/archive/0.4.0.tar.gz
Keywords: xls,excel,spreadsheet,workbook,xlsx,csv,txt
Platform: UNKNOWN
Classifier: Programming Language :: Python
Classifier: Programming Language :: Python :: 2
Classifier: Programming Language :: Python :: 3
Classifier: Operating System :: OS Independent
Classifier: Topic :: Database
Classifier: Topic :: Office/Business
Classifier: Topic :: Software Development :: Libraries :: Python Modules
